easyaspi/__init__.py
easyaspi-2018.3.dist-info/LICENSE.txt
easyaspi-2018.3.dist-info/METADATA
easyaspi-2018.3.dist-info/WHEEL
easyaspi-2018.3.dist-info/top_level.txt
easyaspi-2018.3.dist-info/RECORD
