Metadata-Version: 2.1
Name: easyaspi
Version: 2018.3
Summary: A module intended to abstract away a lot of the complexity of using the GPIO and PiCamera for beginner programmers.
Home-page: https://github.com/pypa/easyaspi
Author: Paul Baumgarten
Author-email: pbaumgarten@gmail.com
License: UNKNOWN
Keywords: raspberrypi GPIO picamera beginner
Platform: UNKNOWN
Classifier: Programming Language :: Python :: 3
Classifier: License :: OSI Approved :: MIT License
Classifier: Operating System :: OS Independent
Requires-Python: >=3
Requires-Dist: rpi.gpio
Requires-Dist: picamera
